beaker_redis.py
beaker_redis-1.1.0.dist-info/METADATA
beaker_redis-1.1.0.dist-info/RECORD
beaker_redis-1.1.0.dist-info/WHEEL
beaker_redis-1.1.0.dist-info/entry_points.txt
beaker_redis-1.1.0.dist-info/top_level.txt
