Metadata-Version: 2.1
Name: beaker-redis
Version: 1.1.0
Summary: Beaker backend for redis
Home-page: https://github.com/zzzsochi/beaker_redis
Author: Zelenyak "ZZZ" Aleksander
Author-email: zzz.sochi@gmail.com
License: BSD
Platform: any
Classifier: Development Status :: 5 - Production/Stable
Classifier: Intended Audience :: Developers
Classifier: Operating System :: OS Independent
Classifier: Programming Language :: Python :: 3
Requires-Dist: beaker
Requires-Dist: redis
